wcst_converter/__init__.py
wcst_converter/app.py
wcst_converter-0.0.2.dist-info/LICENSE.txt
wcst_converter-0.0.2.dist-info/METADATA
wcst_converter-0.0.2.dist-info/WHEEL
wcst_converter-0.0.2.dist-info/entry_points.txt
wcst_converter-0.0.2.dist-info/top_level.txt
wcst_converter-0.0.2.dist-info/RECORD
