Metadata-Version: 2.1
Name: wcst-converter
Version: 0.0.2
Summary: Convert WCST output reports to collapsed columns format
Home-page: http://www.ericvanbuhler.net
Author: Eric VanBuhler
Author-email: eric.vanbuhler@gmail.com
License: UNKNOWN
Platform: UNKNOWN
Classifier: Programming Language :: Python :: 3
Classifier: License :: OSI Approved :: MIT License
Classifier: Operating System :: OS Independent
Requires-Python: >=3.6
Requires-Dist: numpy (==1.18.4)
Requires-Dist: pandas (==1.0.3)
